{
  "trainingPhrases": [ {
    "parts": [ {
      "text": "결제패이지",
      "auto": true
    } ],
    "repeatCount": 1,
    "languageCode": "ko"
  }, {
    "parts": [ {
      "text": "결제페이지",
      "auto": true
    } ],
    "repeatCount": 2,
    "languageCode": "ko"
  }, {
    "parts": [ {
      "text": "결제페이지로",
      "auto": true
    } ],
    "repeatCount": 1,
    "languageCode": "ko"
  }, {
    "parts": [ {
      "text": "결제로",
      "auto": true
    } ],
    "repeatCount": 1,
    "languageCode": "ko"
  }, {
    "parts": [ {
      "text": "걸재",
      "auto": true
    } ],
    "repeatCount": 1,
    "languageCode": "ko"
  }, {
    "parts": [ {
      "text": "걸제",
      "auto": true
    } ],
    "repeatCount": 1,
    "languageCode": "ko"
  }, {
    "parts": [ {
      "text": "결재",
      "auto": true
    } ],
    "repeatCount": 1,
    "languageCode": "ko"
  }, {
    "parts": [ {
      "text": "결제",
      "auto": true
    } ],
    "repeatCount": 1,
    "languageCode": "ko"
  } ]
}
